ltk/__init__.py
ltk/jquery.py
ltk/logger.py
ltk/ltk.css
ltk/ltk.js
ltk/pubsub.py
ltk/widgets.py
pyscript_ltk-0.2.30.dist-info/LICENSE
pyscript_ltk-0.2.30.dist-info/METADATA
pyscript_ltk-0.2.30.dist-info/WHEEL
pyscript_ltk-0.2.30.dist-info/top_level.txt
pyscript_ltk-0.2.30.dist-info/RECORD
