Metadata-Version: 2.2
Name: pyscript-ltk
Version: 0.2.30
Summary: A little toolkit for writing UIs in PyScript
Author-email: Chris Laffra <chris@chrislaffra.com>
License:                                  Apache License
Project-URL: Homepage, https://github.com/laffra/ltk
Keywords: jquery,pyscript,ui,widgets,css
Classifier: Programming Language :: Python
Classifier: Programming Language :: Python :: 3
Requires-Python: >=3.8
License-File: LICENSE
Provides-Extra: dev
Requires-Dist: mock; extra == "dev"
Requires-Dist: pytest; extra == "dev"
